ray_log_notebook/__init__.py
ray_log_notebook/capture.py
ray_log_notebook/py.typed
ray_log_notebook-0.0.1.dist-info/WHEEL
ray_log_notebook-0.0.1.dist-info/METADATA
ray_log_notebook-0.0.1.dist-info/RECORD
