Metadata-Version: 2.4
Name: ray-log-notebook
Version: 0.0.1
Summary: Capture and redir ray logs in Jupyter Notebook.
Keywords: ray,log,IPython,jupyter,notebook
Author: Clouder0
Author-email: Clouder0 <clouder0@outlook.com>
License-Expression: MIT
Classifier: Development Status :: 3 - Alpha
Classifier: Intended Audience :: Developers
Classifier: Programming Language :: Python :: 3
Classifier: Programming Language :: Python :: 3.12
Classifier: Programming Language :: Python :: 3.13
Classifier: Programming Language :: Python :: 3.14
Requires-Dist: ray>=2.49.0
Requires-Python: >=3.12
Project-URL: Repository, https://github.com/clouder0/ray-log-notebook.git
